setup.py
SHERBIN/__init__.py
SHERBIN/sher.py
SHERBIN.egg-info/PKG-INFO
SHERBIN.egg-info/SOURCES.txt
SHERBIN.egg-info/dependency_links.txt
SHERBIN.egg-info/not-zip-safe
SHERBIN.egg-info/top_level.txt