Metadata-Version: 1.0
Name: SHERBIN
Version: 0.1
Summary: SHER_EMAIL
Home-page: UNKNOWN
Author: UNKNOWN
Author-email: UNKNOWN
License: UNKNOWN
Platform: UNKNOWN
